[
    {
        "content": [
            {
                "x": 576,
                "y": 190
            },
            {
                "x": 566,
                "y": 168
            },
            {
                "x": 580,
                "y": 153
            },
            {
                "x": 597,
                "y": 146
            },
            {
                "x": 612,
                "y": 139
            },
            {
                "x": 627,
                "y": 125
            },
            {
                "x": 662,
                "y": 114
            },
            {
                "x": 705,
                "y": 117
            },
            {
                "x": 710,
                "y": 132
            },
            {
                "x": 717,
                "y": 154
            },
            {
                "x": 712,
                "y": 172
            },
            {
                "x": 686,
                "y": 184
            },
            {
                "x": 648,
                "y": 182
            },
            {
                "x": 630,
                "y": 191
            },
            {
                "x": 616,
                "y": 199
            },
            {
                "x": 586,
                "y": 198
            }
        ],
        "rectMask": {
            "xMin": 566,
            "yMin": 114,
            "width": 151,
            "height": 85
        },
        "labels": {
            "labelName": "Nissan",
            "labelColor": "#0004ff",
            "labelColorRGB": "0,4,255",
            "visibility": true
        },
        "labelLocation": {
            "x": 641.5,
            "y": 156.5
        },
        "contentType": "polygon"
    }
]